setup.py
ProtoText/__init__.py
ProtoText/hook_helper.py
ProtoText/models.py
ProtoText.egg-info/PKG-INFO
ProtoText.egg-info/SOURCES.txt
ProtoText.egg-info/dependency_links.txt
ProtoText.egg-info/requires.txt
ProtoText.egg-info/top_level.txt