Metadata-Version: 1.0
Name: ProtoText
Version: 0.3.3
Summary: ProtoText is a powerful python dict-like wrapper class to process google protobuf objects.
Home-page: https://github.com/XericZephyr/prototext
Author: Zheng Xu
Author-email: xuzheng1111@gmail.com
License: MIT
Keywords: protobuf,dict
Platform: UNKNOWN
